[
    {
        "url": "https://raw.githubusercontent.com/itsmeimad65/cloudstream-extensions-imad/builds/FreeSidePlus.cs3",
        "status": 1,
        "version": 2,
        "name": "FreeSidePlus",
        "internalName": "FreeSidePlus",
        "authors": [
            "imad"
        ],
        "description": "Free Side+ content - Sidecast, BTS, Side+ Saturdays, Inside, 1v100",
        "fileSize": 32237,
        "repositoryUrl": "https://github.com/itsmeimad65/cloudstream-extensions-imad",
        "language": "en",
        "tvTypes": [
            "Movie",
            "TvSeries"
        ],
        "iconUrl": "https://www.free-sideplus.com/wp-content/uploads/2026/03/ontario-logo-dark-mode-2.webp",
        "apiVersion": 1,
        "fileHash": "sha256-6971f682946f71dc36362004f5720d2f95fcd72bbaace42e85a165e73e4c49b1"
    }
]